spatialcell/__init__.py
spatialcell/cell_annotation/__init__.py
spatialcell/cell_annotation/annotation_processor.py
spatialcell/cell_annotation/annotation_visualizer.py
spatialcell/cell_annotation/classifier_trainer.py
spatialcell/cell_annotation/rds_extractor.R
spatialcell/cell_annotation/rds_processor.py
spatialcell/preprocessing/__init__.py
spatialcell/preprocessing/svg_to_npz.py
spatialcell/qupath_scripts/ROIExtractor.groovy
spatialcell/qupath_scripts/nucleus_detection.groovy
spatialcell/spatial_segmentation/__init__.py
spatialcell/spatial_segmentation/spatial_processor.py
spatialcell/utils/Xinyantopact.py
spatialcell/utils/__init__.py
spatialcell/utils/color_schemes.py
spatialcell/utils/config_manager.py
spatialcell/utils/rename_utils.py
spatialcell/utils/roi_extractor.py
spatialcell/utils/roi_validator.py
spatialcell/utils/spatial_analysis.py
spatialcell-1.1.1.dist-info/licenses/LICENSE
spatialcell-1.1.1.dist-info/METADATA
spatialcell-1.1.1.dist-info/WHEEL
spatialcell-1.1.1.dist-info/entry_points.txt
spatialcell-1.1.1.dist-info/top_level.txt
spatialcell-1.1.1.dist-info/RECORD
