Metadata-Version: 2.4
Name: spatialcell
Version: 1.1.1
Summary: Integrated pipeline for spatial transcriptomics cell segmentation and annotation using QuPath, Bin2cell, and TopAct
Home-page: https://github.com/Xinyan-C/Spatialcell
Author: Xinyan
Author-email: Xinyan <keepandon@gmail.com>
License-Expression: Apache-2.0
Project-URL: Homepage, https://github.com/Xinyan-C/Spatialcell
Project-URL: Documentation, https://github.com/Xinyan-C/Spatialcell#readme
Project-URL: Repository, https://github.com/Xinyan-C/Spatialcell
Project-URL: Bug Reports, https://github.com/Xinyan-C/Spatialcell/issues
Project-URL: Source Code, https://github.com/Xinyan-C/Spatialcell
Project-URL: Changelog, https://github.com/Xinyan-C/Spatialcell/releases
Keywords: spatial-transcriptomics,cell-segmentation,cell-annotation,QuPath,Bin2cell,TopAct,bioinformatics,single-cell
Classifier: Development Status :: 4 - Beta
Classifier: Intended Audience :: Science/Research
Classifier: Topic :: Scientific/Engineering :: Bio-Informatics
Classifier: Programming Language :: Python :: 3
Classifier: Programming Language :: Python :: 3.8
Classifier: Programming Language :: Python :: 3.9
Classifier: Programming Language :: Python :: 3.10
Classifier: Programming Language :: Python :: 3.11
Classifier: Operating System :: OS Independent
Requires-Python: >=3.10
License-File: LICENSE
Requires-Dist: numpy>=1.21.0
Requires-Dist: pandas>=1.3.0
Requires-Dist: scipy>=1.7.0
Requires-Dist: opencv-python>=4.5.0
Requires-Dist: Pillow>=8.0.0
Requires-Dist: matplotlib>=3.5.0
Requires-Dist: colorcet>=2.0.0
Requires-Dist: scanpy>=1.8.0
Requires-Dist: scikit-learn>=1.0.0
Requires-Dist: joblib>=1.1.0
Requires-Dist: natsort>=8.0.0
Requires-Dist: tqdm>=4.60.0
Requires-Dist: pyyaml>=6.0
Requires-Dist: tensorflow==2.19.0
Requires-Dist: bin2cell>=0.3.0
Provides-Extra: dev
Requires-Dist: pytest>=6.0; extra == "dev"
Requires-Dist: black>=22.0; extra == "dev"
Requires-Dist: flake8>=4.0; extra == "dev"
Requires-Dist: mypy>=0.950; extra == "dev"
Requires-Dist: jupyter>=1.0.0; extra == "dev"
Requires-Dist: ipykernel>=6.0.0; extra == "dev"
Provides-Extra: docs
Requires-Dist: sphinx>=4.0; extra == "docs"
Requires-Dist: sphinx-rtd-theme>=1.0; extra == "docs"
Requires-Dist: myst-parser>=0.18.0; extra == "docs"
Provides-Extra: extra
Requires-Dist: seaborn>=0.11.0; extra == "extra"
Requires-Dist: plotly>=5.0.0; extra == "extra"
Requires-Dist: kaleido>=0.2.1; extra == "extra"
Provides-Extra: all
Requires-Dist: pytest>=6.0; extra == "all"
Requires-Dist: black>=22.0; extra == "all"
Requires-Dist: flake8>=4.0; extra == "all"
Requires-Dist: mypy>=0.950; extra == "all"
Requires-Dist: jupyter>=1.0.0; extra == "all"
Requires-Dist: ipykernel>=6.0.0; extra == "all"
Requires-Dist: sphinx>=4.0; extra == "all"
Requires-Dist: sphinx-rtd-theme>=1.0; extra == "all"
Requires-Dist: myst-parser>=0.18.0; extra == "all"
Requires-Dist: seaborn>=0.11.0; extra == "all"
Requires-Dist: plotly>=5.0.0; extra == "all"
Requires-Dist: kaleido>=0.2.1; extra == "all"
Dynamic: author
Dynamic: home-page
Dynamic: license-file
Dynamic: requires-python
